Workbook

Sheet Anleitung
B2: Fahrtenbuch für Selbstständige
B4: Warum ein Fahrtenbuch?
B5: Nutzt du ein Fahrzeug aus dem Betriebsvermögen auch privat, musst du den
B6: privaten Anteil versteuern. Dafür gibt es zwei Wege:
B8: 1-%-Regelung: Pauschal 1 % des Bruttolistenpreises pro Monat.
B9: Einfach, aber oft teuer — besonders bei teuren Fahrzeugen und
B10: wenig Privatnutzung.
B12: Fahrtenbuch: Du weist den tatsächlichen Privatanteil nach und
B13: versteuerst nur diesen. Mehr Aufwand, aber meist deutlich günstiger.
B15: Diese Vorlage rechnet dir beides aus und zeigt, welcher Weg für dich
B16: günstiger ist.
B18: Die vier Anforderungen des Finanzamts
... B48: entscheidet im Einzelfall das Finanzamt. Stand: August 2026.

Sheet Fahrzeug
B2: Fahrzeugdaten
B3: Einmalig ausfüllen.
B5: Fahrzeug (Marke, Modell) | C5: VW Caddy
B6: Amtliches Kennzeichen | C6: KN-XY 123
B7: Bruttolistenpreis bei Erstzulassung | C7: 32000 | D7: Neupreis laut Liste, auch bei Gebrauchtkauf. Basis für die 1-%-Regelung.
B8: Kilometerstand am 1.1. | C8: 15000
B9: Wirtschaftsjahr | C9: 2026
B10: Entfernung Wohnung–Betrieb (km) | C10: 12 | D10: Einfache Strecke. Für die Pendlerpauschale.
B11: Gesamtkosten Fahrzeug pro Jahr | C11: 6800 | D11: Abschreibung, Sprit, Versicherung, Wartung, Steuer.
B12: Persönlicher Steuersatz | C12: 0.3 | D12: Grobe Näherung für den Vergleich.

Sheet Fahrtenbuch
A1: Fahrtenbuch
A2: Jede Fahrt sofort eintragen. Am Monatsende ausdrucken und aufbewahren.
A4: Datum | B4: km Beginn | C4: km Ende | D4: gefahren | E4: Art der Fahrt | F4: Reiseziel (Ort, Straße) | G4: Reisezweck | H4: Geschäftspartner / Kunde | I4: Prüfung
A5: 2026-01-08 | B5: 15000 | C5: 15042 | D5: =IF(OR(B5="",C5=""),"",C5-B5) | E5: betrieblich | F5: Singen, Industriestr. 4 | G5: Standortbesichtigung | H5: Muster GmbH | I5: =IF(A5="","",IF(C5<B5,"km Ende < km Beginn",IF(AND(ROW()>5,B5<>"",INDEX($C$5:$C$404,ROW()-5)<>"",B5<>INDEX($C$5:$C$404,ROW()-5)),"LÜCKE im km-Stand",IF(AND(E5="betrieblich",OR(F5="",G5="",H5="")),"Pflichtangabe fehlt","ok"))))
D6: =IF(OR(B6="",C6=""),"",C6-B6) | I6: =IF(A6="","",IF(C6<B6,"km Ende < km Beginn",IF(AND(ROW()>5,B6<>"",INDEX($C$5:$C$404,ROW()-5)<>"",B6<>INDEX($C$5:$C$404,ROW()-5)),"LÜCKE im km-Stand",IF(AND(E6="betrieblich",OR(F6="",G6="",H6="")),"Pflichtangabe fehlt","ok"))))
D7: =IF(OR(B7="",C7=""),"",C7-B7) | I7: =IF(A7="","",IF(C7<B7,"km Ende < km Beginn",IF(AND(ROW()>5,B7<>"",INDEX($C$5:$C$404,ROW()-5)<>"",B7<>INDEX($C$5:$C$404,ROW()-5)),"LÜCKE im km-Stand",IF(AND(E7="betrieblich",OR(F7="",G7="",H7="")),"Pflichtangabe fehlt","ok"))))
D8: =IF(OR(B8="",C8=""),"",C8-B8) | I8: =IF(A8="","",IF(C8<B8,"km Ende < km Beginn",IF(AND(ROW()>5,B8<>"",INDEX($C$5:$C$404,ROW()-5)<>"",B8<>INDEX($C$5:$C$404,ROW()-5)),"LÜCKE im km-Stand",IF(AND(E8="betrieblich",OR(F8="",G8="",H8="")),"Pflichtangabe fehlt","ok"))))
D9: =IF(OR(B9="",C9=""),"",C9-B9) | I9: =IF(A9="","",IF(C9<B9,"km Ende < km Beginn",IF(AND(ROW()>5,B9<>"",INDEX($C$5:$C$404,ROW()-5)<>"",B9<>INDEX($C$5:$C$404,ROW()-5)),"LÜCKE im km-Stand",IF(AND(E9="betrieblich",OR(F9="",G9="",H9="")),"Pflichtangabe fehlt","ok"))))
D10: =IF(OR(B10="",C10=""),"",C10-B10) | I10: =IF(A10="","",IF(C10<B10,"km Ende < km Beginn",IF(AND(ROW()>5,B10<>"",INDEX($C$5:$C$404,ROW()-5)<>"",B10<>INDEX($C$5:$C$404,ROW()-5)),"LÜCKE im km-Stand",IF(AND(E10="betrieblich",OR(F10="",G10="",H10="")),"Pflichtangabe fehlt","ok"))))
D11: =IF(OR(B11="",C11=""),"",C11-B11) | I11: =IF(A11="","",IF(C11<B11,"km Ende < km Beginn",IF(AND(ROW()>5,B11<>"",INDEX($C$5:$C$404,ROW()-5)<>"",B11<>INDEX($C$5:$C$404,ROW()-5)),"LÜCKE im km-Stand",IF(AND(E11="betrieblich",OR(F11="",G11="",H11="")),"Pflichtangabe fehlt","ok"))))
D12: =IF(OR(B12="",C12=""),"",C12-B12) | I12: =IF(A12="","",IF(C12<B12,"km Ende < km Beginn",IF(AND(ROW()>5,B12<>"",INDEX($C$5:$C$404,ROW()-5)<>"",B12<>INDEX($C$5:$C$404,ROW()-5)),"LÜCKE im km-Stand",IF(AND(E12="betrieblich",OR(F12="",G12="",H12="")),"Pflichtangabe fehlt","ok"))))
D13: =IF(OR(B13="",C13=""),"",C13-B13) | I13: =IF(A13="","",IF(C13<B13,"km Ende < km Beginn",IF(AND(ROW()>5,B13<>"",INDEX($C$5:$C$404,ROW()-5)<>"",B13<>INDEX($C$5:$C$404,ROW()-5)),"LÜCKE im km-Stand",IF(AND(E13="betrieblich",OR(F13="",G13="",H13="")),"Pflichtangabe fehlt","ok"))))
D14: =IF(OR(B14="",C14=""),"",C14-B14) | I14: =IF(A14="","",IF(C14<B14,"km Ende < km Beginn",IF(AND(ROW()>5,B14<>"",INDEX($C$5:$C$404,ROW()-5)<>"",B14<>INDEX($C$5:$C$404,ROW()-5)),"LÜCKE im km-Stand",IF(AND(E14="betrieblich",OR(F14="",G14="",H14="")),"Pflichtangabe fehlt","ok"))))
D15: =IF(OR(B15="",C15=""),"",C15-B15) | I15: =IF(A15="","",IF(C15<B15,"km Ende < km Beginn",IF(AND(ROW()>5,B15<>"",INDEX($C$5:$C$404,ROW()-5)<>"",B15<>INDEX($C$5:$C$404,ROW()-5)),"LÜCKE im km-Stand",IF(AND(E15="betrieblich",OR(F15="",G15="",H15="")),"Pflichtangabe fehlt","ok"))))
D16: =IF(OR(B16="",C16=""),"",C16-B16) | I16: =IF(A16="","",IF(C16<B16,"km Ende < km Beginn",IF(AND(ROW()>5,B16<>"",INDEX($C$5:$C$404,ROW()-5)<>"",B16<>INDEX($C$5:$C$404,ROW()-5)),"LÜCKE im km-Stand",IF(AND(E16="betrieblich",OR(F16="",G16="",H16="")),"Pflichtangabe fehlt","ok"))))
D17: =IF(OR(B17="",C17=""),"",C17-B17) | I17: =IF(A17="","",IF(C17<B17,"km Ende < km Beginn",IF(AND(ROW()>5,B17<>"",INDEX($C$5:$C$404,ROW()-5)<>"",B17<>INDEX($C$5:$C$404,ROW()-5)),"LÜCKE im km-Stand",IF(AND(E17="betrieblich",OR(F17="",G17="",H17="")),"Pflichtangabe fehlt","ok"))))
... D404: =IF(OR(B404="",C404=""),"",C404-B404) | I404: =IF(A404="","",IF(C404<B404,"km Ende < km Beginn",IF(AND(ROW()>5,B404<>"",INDEX($C$5:$C$404,ROW()-5)<>"",B404<>INDEX($C$5:$C$404,ROW()-5)),"LÜCKE im km-Stand",IF(AND(E404="betrieblich",OR(F404="",G404="",H404="")),"Pflichtangabe fehlt","ok"))))

Sheet Auswertung
B2: Auswertung
B5: Gefahrene Kilometer
B6: betrieblich | C6: =SUMIF(Fahrtenbuch!$E$5:$E$404,"betrieblich",Fahrtenbuch!$D$5:$D$404)
B7: Fahrten Wohnung–Betrieb | C7: =SUMIF(Fahrtenbuch!$E$5:$E$404,"Fahrt Wohnung–Betrieb",Fahrtenbuch!$D$5:$D$404)
B8: privat | C8: =SUMIF(Fahrtenbuch!$E$5:$E$404,"privat",Fahrtenbuch!$D$5:$D$404)
B9: Gesamt | C9: =C6+C7+C8
B10: Privatanteil in Prozent | C10: =IF(C9=0,0,C8/C9) | D10: Nur dieser Anteil der Fahrzeugkosten ist privat und muss versteuert werden.
B12: Vergleich: Fahrtenbuch oder 1-%-Regelung
B13: Geldwerter Vorteil laut Fahrtenbuch | C13: =Fahrzeug!C11*C10 | D13: Tatsächliche Kosten mal Privatanteil.
B14: Geldwerter Vorteil laut 1-%-Regelung | C14: =Fahrzeug!C7*0.01*12 | D14: 1 % des Bruttolistenpreises pro Monat.
B15: Unterschied | C15: =C14-C13 | D15: Positiv heißt: Das Fahrtenbuch spart dir diesen Betrag an zu versteuerndem Vorteil.
B16: Steuerersparnis geschätzt | C16: =MAX(0,C15)*Fahrzeug!C12 | D16: Grobe Näherung mit deinem Steuersatz.
B18: EMPFEHLUNG | C18: =IF(C9=0,"Noch keine Fahrten erfasst",IF(C15>0,"Fahrtenbuch lohnt sich","1-%-Regelung ist günstiger"))
B20: Kontrolle der Vollständigkeit
B21: Fahrten erfasst | C21: =COUNTIF(Fahrtenbuch!$A$5:$A$404,"<>")
B22: Beanstandete Zeilen | C22: =COUNTIFS(Fahrtenbuch!$I$5:$I$404,"<>ok",Fahrtenbuch!$I$5:$I$404,"<>") | D22: Muss 0 sein. Die Spalte „Prüfung“ im Fahrtenbuch zeigt, was fehlt.
B24: Denk daran: monatlich ausdrucken oder als PDF sichern.
B25: Eine Excel-Datei allein erfüllt die geschlossene Form nicht.
B27: Arbeitshilfe, keine Steuerberatung. Stand: August 2026.
