Workbook

Sheet Anleitung
B2: Stundensatz- und Preiskalkulator
B4: Warum die übliche Rechnung falsch ist
B5: Die meisten rechnen: Wunschgehalt geteilt durch 2.000 Stunden im Jahr.
B6: Das ist der teuerste Rechenfehler in der Selbstständigkeit.
B8: Warum? Weil du nicht 2.000 Stunden verkaufen kannst. Urlaub, Krankheit,
B9: Feiertage, Angebote schreiben, Buchhaltung, Akquise, Weiterbildung —
B10: all das kostet Zeit, die niemand bezahlt. Realistisch bleiben von 2.000
B11: Stunden etwa 1.000 bis 1.200 fakturierbare übrig.
B13: Dazu kommen Steuern, Krankenversicherung und Altersvorsorge, die bei
B14: Angestellten der Arbeitgeber mitträgt. Als Selbstständiger zahlst du alles.
B16: So arbeitest du damit
B17: 1. Blatt „Kalkulation“ öffnen und die gelben Felder ausfüllen.
... B35: Stand: August 2026.

Sheet Kalkulation
B2: Dein Mindest-Stundensatz
B3: Gelbe Felder ausfüllen. Alles andere rechnet sich automatisch.
B5: 1. Was du zum Leben brauchst
B6: Gewünschtes Netto pro Monat | C6: 2500 | D6: Was am Monatsende auf deinem Privatkonto ankommen soll.
B7: Netto pro Jahr | C7: =C6*12
B9: 2. Was zusätzlich abgeht
B10: Einkommensteuer, geschätzt in % | C10: 0.25 | D10: Grobe Näherung. Bei 30.000–50.000 € Gewinn meist 20–30 %.
B11: Krankenversicherung pro Monat | C11: 450 | D11: Freiwillig gesetzlich versichert: meist 350–550 €. Privat variiert stark.
B12: Altersvorsorge pro Monat | C12: 300 | D12: Als Selbstständiger zahlt das niemand für dich. Nicht weglassen.
B13: Summe Vorsorge pro Jahr | C13: =(C11+C12)*12
B14: Nötiger Gewinn vor Steuern | C14: =(C7+C13)/(1-C10) | D14: Rückwärts gerechnet: Von diesem Betrag bleibt nach Steuern und Vorsorge dein Wunsch-Netto übrig.
B16: 3. Deine Betriebskosten
B17: Büro oder Arbeitszimmer pro Monat | C17: 200 | D17: Miete, Strom, Reinigung.
B18: Telefon, Internet, Mobilfunk | C18: 60
B19: Software, Werkzeuge, Lizenzen | C19: 80 | D19: Buchhaltung, Fachsoftware, Cloud.
B20: Versicherungen (betrieblich) | C20: 50 | D20: Betriebshaftpflicht, Rechtsschutz.
B21: Fahrzeug und Fahrtkosten | C21: 250 | D21: Leasing, Sprit, Wartung, ÖPNV.
B22: Steuerberater und Buchhaltung | C22: 120
B23: Weiterbildung und Fachliteratur | C23: 60
B24: Werbung und Website | C24: 50
B25: Sonstiges und Puffer | C25: 100 | D25: Was immer dazwischenkommt.
B26: Betriebskosten pro Jahr | C26: =SUM(C17:C25)*12
B28: 4. Deine verkaufbare Zeit
B29: Arbeitsstunden pro Woche | C29: 40
B30: Arbeitswochen pro Jahr | C30: 52
B31: Urlaubswochen | C31: 6 | D31: Nimm dir echten Urlaub. Wer 0 einträgt, kalkuliert sich in den Burnout.
B32: Krankheitswochen | C32: 2 | D32: Auch Selbstständige werden krank. Realistisch: 2 Wochen.
B33: Feiertage in Wochen | C33: 2
B34: Arbeitswochen effektiv | C34: =C30-C31-C32-C33
B35: Bruttoarbeitsstunden pro Jahr | C35: =C34*C29
B36: Anteil unbezahlte Arbeit in % | C36: 0.35 | D36: Angebote, Buchhaltung, Akquise, Weiterbildung, E-Mails. Realistisch 30–45 %.
B37: Verkaufbare Stunden pro Jahr | C37: =C35*(1-C36) | D37: Nur diese Stunden kannst du in Rechnung stellen.
B39: 5. Ergebnis
B40: Nötiger Jahresumsatz | C40: =C14+C26
B42: MINDEST-STUNDENSATZ (netto) | C42: =IF(C37<=0,"",C40/C37) | D42: Das ist die Untergrenze, nicht dein Wunschpreis. Darunter arbeitest du mit Verlust.
B44: Tagessatz (8 Stunden) | C44: =C42*8
B45: Empfohlener Angebotssatz (+20 % Puffer) | C45: =C42*1.2 | D45: Der Mindestsatz lässt keinen Raum für Rabatte, Ausfälle oder Investitionen.
B47: Näherungsrechnung, keine Steuerberatung. Steuersatz ist geschätzt.

Sheet Projektpreis
B2: Einzelnes Projekt kalkulieren
B3: Für Festpreis-Angebote. Der Stundensatz kommt automatisch aus dem Blatt „Kalkulation“.
B5: Arbeitspaket | C5: Stunden | D5: Stundensatz | E5: Summe
B6: Beispiel: Konzept und Abstimmung | C6: 8 | D6: =Kalkulation!$C$42 | E6: =IF(C6="","",C6*D6)
D7: =Kalkulation!$C$42 | E7: =IF(C7="","",C7*D7)
D8: =Kalkulation!$C$42 | E8: =IF(C8="","",C8*D8)
D9: =Kalkulation!$C$42 | E9: =IF(C9="","",C9*D9)
D10: =Kalkulation!$C$42 | E10: =IF(C10="","",C10*D10)
D11: =Kalkulation!$C$42 | E11: =IF(C11="","",C11*D11)
D12: =Kalkulation!$C$42 | E12: =IF(C12="","",C12*D12)
D13: =Kalkulation!$C$42 | E13: =IF(C13="","",C13*D13)
D14: =Kalkulation!$C$42 | E14: =IF(C14="","",C14*D14)
D15: =Kalkulation!$C$42 | E15: =IF(C15="","",C15*D15)
D16: =Kalkulation!$C$42 | E16: =IF(C16="","",C16*D16)
D17: =Kalkulation!$C$42 | E17: =IF(C17="","",C17*D17)
D18: =Kalkulation!$C$42 | E18: =IF(C18="","",C18*D18)
... D25: =Kalkulation!$C$42 | E25: =IF(C25="","",C25*D25)
D27: Summe Arbeitszeit | E27: =SUM(E6:E25)
D28: Materialkosten | E28: 0
D29: Risikoaufschlag in % | E29: 0.15
D30: ANGEBOTSPREIS (netto) | E30: =(E27+E28)*(1+E29)
B32: Der Risikoaufschlag deckt ab, dass Projekte fast immer länger dauern als geschätzt.

Sheet Vergleich
B2: Was verschiedene Stundensätze bedeuten
B3: Basis: deine verkaufbaren Stunden und Kosten aus dem Blatt „Kalkulation“.
B5: Stundensatz | C5: 40 | D5: 60 | E5: 80 | F5: 100 | G5: 120
B6: Jahresumsatz | C6: =C$5*Kalkulation!$C$37 | D6: =D$5*Kalkulation!$C$37 | E6: =E$5*Kalkulation!$C$37 | F6: =F$5*Kalkulation!$C$37 | G6: =G$5*Kalkulation!$C$37
B7: minus Betriebskosten | C7: =-Kalkulation!$C$26 | D7: =-Kalkulation!$C$26 | E7: =-Kalkulation!$C$26 | F7: =-Kalkulation!$C$26 | G7: =-Kalkulation!$C$26
B8: Gewinn vor Steuern | C8: =C6+C7 | D8: =D6+D7 | E8: =E6+E7 | F8: =F6+F7 | G8: =G6+G7
B9: minus Steuern (geschätzt) | C9: =-MAX(0,C8)*Kalkulation!$C$10 | D9: =-MAX(0,D8)*Kalkulation!$C$10 | E9: =-MAX(0,E8)*Kalkulation!$C$10 | F9: =-MAX(0,F8)*Kalkulation!$C$10 | G9: =-MAX(0,G8)*Kalkulation!$C$10
B10: minus Vorsorge | C10: =-Kalkulation!$C$13 | D10: =-Kalkulation!$C$13 | E10: =-Kalkulation!$C$13 | F10: =-Kalkulation!$C$13 | G10: =-Kalkulation!$C$13
B11: Netto pro Jahr | C11: =C8+C9+C10 | D11: =D8+D9+D10 | E11: =E8+E9+E10 | F11: =F8+F9+F10 | G11: =G8+G9+G10
B12: Netto pro Monat | C12: =C11/12 | D12: =D11/12 | E12: =E11/12 | F12: =F11/12 | G12: =G11/12
B14: Rote Werte bedeuten: Bei diesem Stundensatz machst du Verlust.
B15: Näherungsrechnung mit geschätztem Steuersatz — keine Steuerberatung.
